spconv/__init__.py
spconv/__version__.py
spconv/algo.py
spconv/algocore.py
spconv/build.py
spconv/constants.py
spconv/core.py
spconv/core_cc.cp39-win_amd64.pyd
spconv/cppconstants.py
spconv/debug_utils.py
spconv/test_utils.py
spconv/tools.py
spconv/benchmark/__init__.py
spconv/benchmark/__main__.py
spconv/benchmark/basic.py
spconv/benchmark/core.py
spconv/core_cc/__init__.pyi
spconv/core_cc/csrc/__init__.pyi
spconv/core_cc/csrc/hash/__init__.pyi
spconv/core_cc/csrc/hash/core.pyi
spconv/core_cc/csrc/sparse/__init__.pyi
spconv/core_cc/csrc/sparse/alloc.pyi
spconv/core_cc/csrc/sparse/inference.pyi
spconv/core_cc/csrc/sparse/all/__init__.pyi
spconv/core_cc/csrc/sparse/all/ops1d.pyi
spconv/core_cc/csrc/sparse/all/ops2d.pyi
spconv/core_cc/csrc/sparse/all/ops3d.pyi
spconv/core_cc/csrc/sparse/all/ops4d.pyi
spconv/core_cc/csrc/sparse/all/ops_cpu1d.pyi
spconv/core_cc/csrc/sparse/all/ops_cpu2d.pyi
spconv/core_cc/csrc/sparse/all/ops_cpu3d.pyi
spconv/core_cc/csrc/sparse/all/ops_cpu4d.pyi
spconv/core_cc/csrc/sparse/convops/__init__.pyi
spconv/core_cc/csrc/sparse/convops/convops.pyi
spconv/core_cc/csrc/sparse/convops/gemmops.pyi
spconv/core_cc/csrc/sparse/convops/spops.pyi
spconv/core_cc/csrc/utils/__init__.pyi
spconv/core_cc/csrc/utils/boxops.pyi
spconv/core_cc/csrc/utils/pcc.pyi
spconv/core_cc/cumm/__init__.pyi
spconv/core_cc/cumm/common.pyi
spconv/core_cc/cumm/conv/__init__.pyi
spconv/core_cc/cumm/conv/main.pyi
spconv/core_cc/cumm/gemm/__init__.pyi
spconv/core_cc/cumm/gemm/main.pyi
spconv/csrc/__init__.py
spconv/csrc/hash/__init__.py
spconv/csrc/hash/core.py
spconv/csrc/sparse/__init__.py
spconv/csrc/sparse/all.py
spconv/csrc/sparse/alloc.py
spconv/csrc/sparse/convops.py
spconv/csrc/sparse/cpu_core.py
spconv/csrc/sparse/gather.py
spconv/csrc/sparse/indices.py
spconv/csrc/sparse/inference.py
spconv/csrc/sparse/maxpool.py
spconv/csrc/sparse/pointops.py
spconv/csrc/utils/__init__.py
spconv/csrc/utils/boxops.py
spconv/csrc/utils/launch.py
spconv/csrc/utils/pcc.py
spconv_cu114-2.3.8.dist-info/LICENSE
spconv_cu114-2.3.8.dist-info/METADATA
spconv_cu114-2.3.8.dist-info/WHEEL
spconv_cu114-2.3.8.dist-info/top_level.txt
spconv_cu114-2.3.8.dist-info/RECORD
